dash_qr_manager/DashQrGenerator.py
dash_qr_manager/DashQrReader.py
dash_qr_manager/__init__.py
dash_qr_manager/_imports_.py
dash_qr_manager/dash_qr_manager.min.js
dash_qr_manager/dash_qr_manager.min.js.map
dash_qr_manager/metadata.json
dash_qr_manager/package-info.json
dash_qr_manager-0.0.4.dist-info/LICENSE
dash_qr_manager-0.0.4.dist-info/METADATA
dash_qr_manager-0.0.4.dist-info/WHEEL
dash_qr_manager-0.0.4.dist-info/top_level.txt
dash_qr_manager-0.0.4.dist-info/RECORD
