Metadata-Version: 2.1
Name: dash-qr-manager
Version: 0.0.4
Summary: Dash component to create and read QR codes.
Home-page: https://github.com/Toumaske/dash-qr-manager
Author: Toumaske <krest.toumas@outlook.de>
License: MIT
Platform: UNKNOWN
Classifier: Framework :: Dash
